<annotation>
	<folder>pics</folder>
	<filename>img_0279.jpg</filename>
	<path>C:\Users\ap\Documents\School\Undergraduate\Robotics\Autonomy\Projects\VisionSubsystem\VisionSubsystem\Training Data\tennis-ball-data-mayank\pics\img_0279.jpg</path>
	<source>
		<database>Unknown</database>
	</source>
	<size>
		<width>180</width>
		<height>240</height>
		<depth>3</depth>
	</size>
	<segmented>0</segmented>
	<object>
		<name>tennis ball</name>
		<pose>Unspecified</pose>
		<truncated>0</truncated>
		<difficult>0</difficult>
		<bndbox>
			<xmin>18</xmin>
			<ymin>129</ymin>
			<xmax>40</xmax>
			<ymax>141</ymax>
		</bndbox>
	</object>
	<object>
		<name>tennis ball</name>
		<pose>Unspecified</pose>
		<truncated>1</truncated>
		<difficult>0</difficult>
		<bndbox>
			<xmin>1</xmin>
			<ymin>134</ymin>
			<xmax>34</xmax>
			<ymax>182</ymax>
		</bndbox>
	</object>
	<object>
		<name>tennis ball</name>
		<pose>Unspecified</pose>
		<truncated>0</truncated>
		<difficult>0</difficult>
		<bndbox>
			<xmin>28</xmin>
			<ymin>133</ymin>
			<xmax>62</xmax>
			<ymax>173</ymax>
		</bndbox>
	</object>
	<object>
		<name>tennis ball</name>
		<pose>Unspecified</pose>
		<truncated>0</truncated>
		<difficult>0</difficult>
		<bndbox>
			<xmin>70</xmin>
			<ymin>136</ymin>
			<xmax>104</xmax>
			<ymax>169</ymax>
		</bndbox>
	</object>
	<object>
		<name>tennis ball</name>
		<pose>Unspecified</pose>
		<truncated>0</truncated>
		<difficult>0</difficult>
		<bndbox>
			<xmin>49</xmin>
			<ymin>141</ymin>
			<xmax>99</xmax>
			<ymax>193</ymax>
		</bndbox>
	</object>
</annotation>
